openfisca_nsw_ess_nabers/__init__.py
openfisca_nsw_ess_nabers/parameters/energy_savings_scheme/electricity_certificate_conversion_factor.yaml
openfisca_nsw_ess_nabers/parameters/energy_savings_scheme/gas_certificate_conversion_factor.yaml
openfisca_nsw_ess_nabers/parameters/energy_savings_scheme/maximum_NABERS_star_rating.yaml
openfisca_nsw_ess_nabers/parameters/energy_savings_scheme/table_a21.yaml
openfisca_nsw_ess_nabers/parameters/energy_savings_scheme/NABERS_apartments/AC_coeff.yaml
openfisca_nsw_ess_nabers/parameters/energy_savings_scheme/NABERS_apartments/coeff.yaml
openfisca_nsw_ess_nabers/parameters/energy_savings_scheme/NABERS_apartments/coeff_gym.yaml
openfisca_nsw_ess_nabers/parameters/energy_savings_scheme/NABERS_apartments/condenser_water_coeff.yaml
openfisca_nsw_ess_nabers/parameters/energy_savings_scheme/NABERS_apartments/elec_ghg_coeff.yaml
openfisca_nsw_ess_nabers/parameters/energy_savings_scheme/NABERS_apartments/gas_ghg_coeff.yaml
openfisca_nsw_ess_nabers/parameters/energy_savings_scheme/NABERS_apartments/gym_coeff.yaml
openfisca_nsw_ess_nabers/parameters/energy_savings_scheme/NABERS_apartments/intercept.yaml
openfisca_nsw_ess_nabers/parameters/energy_savings_scheme/NABERS_apartments/lift_coeff.yaml
openfisca_nsw_ess_nabers/parameters/energy_savings_scheme/NABERS_apartments/mech_ventilated_carpark_coeff.yaml
openfisca_nsw_ess_nabers/parameters/energy_savings_scheme/NABERS_apartments/natural_ventilated_carpark_coeff.yaml
openfisca_nsw_ess_nabers/parameters/energy_savings_scheme/NABERS_apartments/pool_coeff.yaml
openfisca_nsw_ess_nabers/parameters/energy_savings_scheme/NABERS_apartments/public_AC_coeff.yaml
openfisca_nsw_ess_nabers/parameters/energy_savings_scheme/NABERS_apartments/public_coeff.yaml
openfisca_nsw_ess_nabers/parameters/energy_savings_scheme/NABERS_apartments/public_coeff_gym.yaml
openfisca_nsw_ess_nabers/parameters/energy_savings_scheme/NABERS_offices/cdd.yaml
openfisca_nsw_ess_nabers-1.3.2.dist-info/LICENSE
openfisca_nsw_ess_nabers-1.3.2.dist-info/METADATA
openfisca_nsw_ess_nabers-1.3.2.dist-info/WHEEL
openfisca_nsw_ess_nabers-1.3.2.dist-info/top_level.txt
openfisca_nsw_ess_nabers-1.3.2.dist-info/RECORD
