Metadata-Version: 2.1
Name: openfisca-nsw-ess-nabers
Version: 1.3.2
Summary: An OpenFisca extension that adds some variables to an already-existing tax and benefit system
Home-page: https://github.com/Openfisca-NSW/openfisca_nsw_ess_nabers
Author: OpenFisca Team
Author-email: sara.falamaki@customerservice.nsw.gov.au
License: http://www.fsf.org/licensing/licenses/agpl-3.0.html
Keywords: benefit microsimulation social tax
Platform: UNKNOWN
Classifier: Development Status :: 5 - Production/Stable
Classifier: License :: OSI Approved :: GNU Affero General Public License v3
Classifier: Operating System :: POSIX
Classifier: Programming Language :: Python
Classifier: Topic :: Scientific/Engineering :: Information Analysis
Requires-Dist: OpenFisca-nsw-base
Requires-Dist: pandas
Requires-Dist: xlrd
Provides-Extra: dev
Requires-Dist: autopep8 (==1.4.4) ; extra == 'dev'
Requires-Dist: flake8 (<3.8.0,>=3.5.0) ; extra == 'dev'
Requires-Dist: flake8-print ; extra == 'dev'
Requires-Dist: pycodestyle (<2.6.0,>=2.3.0) ; extra == 'dev'
